Tan_Soon_Seng.cp313-win_amd64.pyd
Tan_Soon_Seng-0.0.1.dist-info/LICENSE
Tan_Soon_Seng-0.0.1.dist-info/METADATA
Tan_Soon_Seng-0.0.1.dist-info/WHEEL
Tan_Soon_Seng-0.0.1.dist-info/top_level.txt
Tan_Soon_Seng-0.0.1.dist-info/RECORD
